README.txt
fourlth
setup.py
fourlth/__init__.py
fourlth/__main__.py
fourlth/core.py
fourlth/exc.py
fourlth/interp.py
fourlth/loader.py
fourlth.egg-info/PKG-INFO
fourlth.egg-info/SOURCES.txt
fourlth.egg-info/dependency_links.txt
fourlth.egg-info/entry_points.txt
fourlth.egg-info/requires.txt
fourlth.egg-info/top_level.txt
fourlth.egg-info/zip-safe