Metadata-Version: 1.0
Name: fourlth
Version: 0.1.0
Summary: FORTH implementation that can be used with pyramid to pass forth program as URL
Home-page: http://pypi.python.org/pypi/fourlth/
Author: Nick Seidenman
Author-email: seidenman@wehi.edu.au
License: UNKNOWN
Keywords: forth computer language web programming
Platform: UNKNOWN
Classifier: Development Status :: 4 - Beta
Classifier: Environment :: Console
Classifier: License :: OSI Approved :: BSD License
